pycloudimage/__init__.py
pycloudimage/pycloudimage.py
pycloudimage-0.1.4.dist-info/LICENSE
pycloudimage-0.1.4.dist-info/METADATA
pycloudimage-0.1.4.dist-info/WHEEL
pycloudimage-0.1.4.dist-info/top_level.txt
pycloudimage-0.1.4.dist-info/RECORD
