Metadata-Version: 2.1
Name: pycloudimage
Version: 0.1.4
Summary: Get Cloud Image from Internet
Home-page: https://gitee.com/timefiles/pycloudimage
Author: TimeStudio
Author-email: sjgzszg@163.com
License: MIT
Platform: UNKNOWN
Requires-Dist: Pillow
Requires-Dist: pytz
